{
  "id": "intro",
  "title": "Overview",
  "description": "NEXUS is an open-source, production-grade autonomous orchestration platform. It consolidates four prior codebases into one coherent system with full contracts, schemas, tests, and operational tooling:",
  "source": "@site/docs/intro.md",
  "sourceDirName": ".",
  "slug": "/",
  "permalink": "/docs/",
  "draft": false,
  "unlisted": false,
  "editUrl": "https://github.com/Yash-Awasthi/Nexus/edit/main/apps/docs-site/docs/intro.md",
  "tags": [],
  "version": "current",
  "lastUpdatedBy": "Yash Awasthi",
  "lastUpdatedAt": 1781181409000,
  "sidebarPosition": 1,
  "frontMatter": {
    "id": "intro",
    "title": "Overview",
    "sidebar_position": 1,
    "slug": "/"
  },
  "sidebar": "docs",
  "next": {
    "title": "Quick Start",
    "permalink": "/docs/quick-start"
  }
}
